Metadata-Version: 2.1
Name: django-patternfly
Version: 0.0.1
Summary: Patternfly support for Django projects
Home-page: https://github.com/Rintsi/django-patternfly
License: BSD-3-Clause
Keywords: django,django-patternfly,patternfly,theming
Author: Rintsi
Author-email: rintsi@gmail.com
Requires-Python: >=3.6,<4.0
Classifier: Development Status :: 5 - Production/Stable
Classifier: Environment :: Web Environment
Classifier: Framework :: Django
Classifier: Framework :: Django :: 2.2
Classifier: Framework :: Django :: 3.0
Classifier: Intended Audience :: Developers
Classifier: License :: OSI Approved :: BSD License
Classifier: Operating System :: OS Independent
Classifier: Programming Language :: Python :: 3
Classifier: Programming Language :: Python :: 3.6
Classifier: Programming Language :: Python :: 3.7
Classifier: Programming Language :: Python :: 3.8
Classifier: Programming Language :: Python :: 3.9
Classifier: Topic :: Software Development :: Libraries
Classifier: Topic :: Utilities
Provides-Extra: docs
Requires-Dist: beautifulsoup4 (>=4.8.0,<5.0.0)
Requires-Dist: django (>=2.2,<4.0)
Requires-Dist: importlib-metadata (<3); python_version < "3.8"
Requires-Dist: m2r2 (>=0.2.5,<0.3.0); extra == "docs"
Requires-Dist: sphinx (>=2.4,<3.0); extra == "docs"
Requires-Dist: sphinx_rtd_theme (>=0.4.3,<0.5.0); extra == "docs"
Project-URL: Documentation, https://django-patternfly.readthedocs.io/
Project-URL: Repository, https://github.com/Rintsi/django-patternfly
